pypiauto/__init__.py
pypiauto/cli.py
pypiauto/creator.py
pypiauto/publisher.py
pypiauto-0.0.4.dist-info/entry_points.txt
pypiauto-0.0.4.dist-info/METADATA
pypiauto-0.0.4.dist-info/WHEEL
pypiauto-0.0.4.dist-info/RECORD
